{"trial_id": "3", "hyperparameters": {"space": [{"class_name": "Choice", "config": {"name": "optimizer", "default": "rmsprop", "conditions": [], "values": ["rmsprop", "adam", "sgd", "adadelta"], "ordered": false}}], "values": {"optimizer": "sgd"}}, "metrics": {"metrics": {"loss": {"direction": "min", "observations": [{"value": [0.6475818157196045], "step": 4}]}, "accuracy": {"direction": "max", "observations": [{"value": [0.6547231078147888], "step": 4}]}, "val_loss": {"direction": "min", "observations": [{"value": [0.6290442943572998], "step": 4}]}, "val_accuracy": {"direction": "max", "observations": [{"value": [0.701298713684082], "step": 4}]}}}, "score": 0.701298713684082, "best_step": 4, "status": "COMPLETED", "message": null}